{"nodes": [{"id": "coinbase_design_system", "label": "Coinbase Design System", "file_type": "document", "source_file": "design-systems/coinbase/DESIGN.md", "source_location": null, "source_url": null, "captured_at": null, "author": null, "contributor": null}, {"id": "coinbase_crypto", "label": "Coinbase (Crypto)", "file_type": "concept", "source_file": "design-systems/coinbase/DESIGN.md", "source_location": null, "source_url": null, "captured_at": null, "author": null, "contributor": null}, {"id": "fintech_crypto_category", "label": "Fintech & Crypto Category", "file_type": "concept", "source_file": "design-systems/coinbase/DESIGN.md", "source_location": null, "source_url": null, "captured_at": null, "author": null, "contributor": null}, {"id": "coinbase_blue", "label": "Coinbase Blue (#0052ff)", "file_type": "concept", "source_file": "design-systems/coinbase/DESIGN.md", "source_location": null, "source_url": null, "captured_at": null, "author": null, "contributor": null}, {"id": "pill_button_radius", "label": "Pill Button Radius (56px-9999px)", "file_type": "concept", "source_file": "design-systems/coinbase/DESIGN.md", "source_location": null, "source_url": null, "captured_at": null, "author": null, "contributor": null}], "edges": [{"source": "coinbase_design_system", "target": "coinbase_crypto", "relation": "inspired_by", "confidence": "EXTRACTED", "confidence_score": 1.0, "source_file": "design-systems/coinbase/DESIGN.md", "source_location": null, "weight": 1.0}, {"source": "coinbase_design_system", "target": "fintech_crypto_category", "relation": "belongs_to_category", "confidence": "EXTRACTED", "confidence_score": 1.0, "source_file": "design-systems/coinbase/DESIGN.md", "source_location": null, "weight": 1.0}, {"source": "coinbase_design_system", "target": "coinbase_blue", "relation": "uses_brand_color", "confidence": "EXTRACTED", "confidence_score": 1.0, "source_file": "design-systems/coinbase/DESIGN.md", "source_location": null, "weight": 1.0}, {"source": "coinbase_design_system", "target": "pill_button_radius", "relation": "uses_design_token", "confidence": "EXTRACTED", "confidence_score": 1.0, "source_file": "design-systems/coinbase/DESIGN.md", "source_location": null, "weight": 1.0}, {"source": "coinbase_design_system", "target": "dark_theme_pattern", "relation": "uses_color_scheme", "confidence": "INFERRED", "confidence_score": 0.85, "source_file": "design-systems/coinbase/DESIGN.md", "source_location": null, "weight": 1.0}, {"source": "coinbase_design_system", "target": "cal_design_system", "relation": "shares_pill_button_pattern", "confidence": "INFERRED", "confidence_score": 0.55, "source_file": "design-systems/coinbase/DESIGN.md", "source_location": null, "weight": 1.0}], "hyperedges": []}