{"nodes": [{"id": "frame_0050_owl_wolf_tattoo", "label": "Tattoo frame 50 - Owl wings fully spread forward", "file_type": "image", "source_file": "projects/raphael-tattoo/frames/frame-0050.jpg", "source_location": null, "source_url": null, "captured_at": null, "author": null, "contributor": null}], "edges": [{"source": "frame_0050_owl_wolf_tattoo", "target": "frame_0051_owl_wolf_tattoo", "relation": "semantically_similar_to", "confidence": "EXTRACTED", "confidence_score": 1.0, "source_file": "projects/raphael-tattoo/frames/frame-0050.jpg", "source_location": null, "weight": 1.0}], "hyperedges": []}