{"nodes": [{"id": "nike_design", "label": "Nike Design System", "file_type": "document", "source_file": "design-systems/nike/DESIGN.md", "source_location": null, "source_url": null, "captured_at": null, "author": null, "contributor": null}, {"id": "nike_monochrome_ui", "label": "Monochromatic UI Strategy", "file_type": "document", "source_file": "design-systems/nike/DESIGN.md", "source_location": "Section 1", "source_url": null, "captured_at": null, "author": null, "contributor": null}, {"id": "nike_futura_display", "label": "Nike Futura ND Display Typography", "file_type": "document", "source_file": "design-systems/nike/DESIGN.md", "source_location": "Section 3", "source_url": null, "captured_at": null, "author": null, "contributor": null}, {"id": "nike_full_bleed_photo", "label": "Full-Bleed Photography Pattern", "file_type": "document", "source_file": "design-systems/nike/DESIGN.md", "source_location": "Section 4", "source_url": null, "captured_at": null, "author": null, "contributor": null}], "edges": [{"source": "design_system_collection", "target": "nike_design", "relation": "implements", "confidence": "EXTRACTED", "confidence_score": 1.0, "source_file": "design-systems/nike/DESIGN.md", "source_location": null, "weight": 1.0}, {"source": "nike_design", "target": "nike_monochrome_ui", "relation": "references", "confidence": "EXTRACTED", "confidence_score": 1.0, "source_file": "design-systems/nike/DESIGN.md", "source_location": "Section 1", "weight": 1.0}, {"source": "nike_design", "target": "nike_futura_display", "relation": "references", "confidence": "EXTRACTED", "confidence_score": 1.0, "source_file": "design-systems/nike/DESIGN.md", "source_location": "Section 3", "weight": 1.0}, {"source": "nike_design", "target": "nike_full_bleed_photo", "relation": "references", "confidence": "EXTRACTED", "confidence_score": 1.0, "source_file": "design-systems/nike/DESIGN.md", "source_location": "Section 4", "weight": 1.0}, {"source": "nike_design", "target": "dark_theme_pattern", "relation": "conceptually_related_to", "confidence": "INFERRED", "confidence_score": 0.75, "source_file": "design-systems/nike/DESIGN.md", "source_location": null, "weight": 1.0}, {"source": "nike_design", "target": "pill_button_pattern", "relation": "conceptually_related_to", "confidence": "EXTRACTED", "confidence_score": 1.0, "source_file": "design-systems/nike/DESIGN.md", "source_location": null, "weight": 1.0}, {"source": "nike_design", "target": "editorial_typography_pattern", "relation": "conceptually_related_to", "confidence": "INFERRED", "confidence_score": 0.85, "source_file": "design-systems/nike/DESIGN.md", "source_location": null, "weight": 1.0}, {"source": "nike_design", "target": "typography_system_pattern", "relation": "conceptually_related_to", "confidence": "EXTRACTED", "confidence_score": 1.0, "source_file": "design-systems/nike/DESIGN.md", "source_location": null, "weight": 1.0}, {"source": "nike_design", "target": "component_library_pattern", "relation": "conceptually_related_to", "confidence": "EXTRACTED", "confidence_score": 1.0, "source_file": "design-systems/nike/DESIGN.md", "source_location": null, "weight": 1.0}, {"source": "nike_design", "target": "responsive_breakpoint_pattern", "relation": "conceptually_related_to", "confidence": "EXTRACTED", "confidence_score": 1.0, "source_file": "design-systems/nike/DESIGN.md", "source_location": null, "weight": 1.0}], "hyperedges": []}